geomind/__init__.py
geomind/agent.py
geomind/cli.py
geomind/config.py
geomind/tools/__init__.py
geomind/tools/geocoding.py
geomind/tools/processing.py
geomind/tools/stac_search.py
geomind_ai-1.1.1.dist-info/licenses/LICENSE
geomind_ai-1.1.1.dist-info/METADATA
geomind_ai-1.1.1.dist-info/WHEEL
geomind_ai-1.1.1.dist-info/entry_points.txt
geomind_ai-1.1.1.dist-info/top_level.txt
geomind_ai-1.1.1.dist-info/RECORD
